dtd/__init__.py
dtd/autopatch.py
dtd/dtd.py
dtd-0.1.0.dist-info/LICENSE
dtd-0.1.0.dist-info/METADATA
dtd-0.1.0.dist-info/WHEEL
dtd-0.1.0.dist-info/top_level.txt
dtd-0.1.0.dist-info/RECORD
