Metadata-Version: 2.1
Name: dtd
Version: 0.1.0
Summary: Python package to patch all the internal functions to ignore .DS_Store file in Mac
Home-page: https://github.com/muditbac/dtd
Author: Mudit Bachhawat
Author-email: mudit5bachhawat@gmail.com
License: MIT license
Keywords: dtd
Platform: UNKNOWN
Classifier: Development Status :: 2 - Pre-Alpha
Classifier: Intended Audience :: Developers
Classifier: License :: OSI Approved :: MIT License
Classifier: Natural Language :: English
Classifier: Programming Language :: Python :: 3
Classifier: Programming Language :: Python :: 3.5
Classifier: Programming Language :: Python :: 3.6
Classifier: Programming Language :: Python :: 3.7
Classifier: Programming Language :: Python :: 3.8
Requires-Python: >=3.5
